deepmultilingualpunctuation/__init__.py
deepmultilingualpunctuation/punctuationmodel.py
deepmultilingualpunctuation-1.0.1.dist-info/LICENSE
deepmultilingualpunctuation-1.0.1.dist-info/METADATA
deepmultilingualpunctuation-1.0.1.dist-info/WHEEL
deepmultilingualpunctuation-1.0.1.dist-info/top_level.txt
deepmultilingualpunctuation-1.0.1.dist-info/RECORD
