Metadata-Version: 2.1
Name: deepmultilingualpunctuation
Version: 1.0.1
Summary: A python package for deep multilingual punctuation prediction.
Home-page: https://github.com/oliverguhr/deepmultilingualpunctuation
Author: Oliver Guhr
Author-email: oliver.guhr@htw-dresden.de
License: UNKNOWN
Platform: UNKNOWN
Classifier: Programming Language :: Python :: 3
Classifier: License :: OSI Approved :: MIT License
Classifier: Operating System :: OS Independent
Requires-Python: >=3.6
